comaze_gym/__init__.py
comaze_gym/env/__init__.py
comaze_gym/env/comaze_gym_env.py
comaze_gym/env/communication_channel.py
comaze_gym-0.0.1.dist-info/LICENSE
comaze_gym-0.0.1.dist-info/METADATA
comaze_gym-0.0.1.dist-info/WHEEL
comaze_gym-0.0.1.dist-info/top_level.txt
comaze_gym-0.0.1.dist-info/RECORD
