Metadata-Version: 2.1
Name: comaze-gym
Version: 0.0.1
Summary: OpenAI Gym-compatible implementation of the game CoMaze to benchmark AI on Zero-Shot Emergent Coordination and Communication.
Home-page: https://github.com/Near32/comaze-gym
License: UNKNOWN
Platform: UNKNOWN
Classifier: Intended Audience :: Developers
Classifier: Topic :: Scientific/Engineering :: Artificial Intelligence 
Classifier: Programming Language :: Python :: 3
Requires-Python: >=3.6
Requires-Dist: gym
Requires-Dist: gym-minigrid
